{
  "type": "entity",
  "pools": [
    {
      "rolls": 6,
      "bonus_rolls": 2,
      "entries": [
        {
          "type": "minecraft:item",
          "weight":2,
          "functions": [
            {
              "add": false,
              "count": {
                "type": "minecraft:uniform",
                "max": 1.0,
                "min": 0.0
              },
              "function": "minecraft:set_count"
            },
            {
              "count": {
                "type": "minecraft:uniform",
                "max": 1.0,
                "min": 0.0
              },
              "function": "minecraft:looting_enchant"
            }
          ],
          "name": "minecraft:arrow"
        },
        {
          "type": "minecraft:item",
          "weight":2,
          "functions": [
            {
              "add": false,
              "count": {
                "type": "minecraft:uniform",
                "max": 1.0,
                "min": 0.0
              },
              "function": "minecraft:set_count"
            },
            {
              "count": {
                "type": "minecraft:uniform",
                "max": 1.0,
                "min": 0.0
              },
              "function": "minecraft:looting_enchant"
            }
          ],
          "name": "minecraft:coal"
        },
        {
          "type": "empty",
          "weight": 1
        },
        {
          "type": "minecraft:item",
          "weight":1,
          "functions": [
            {
              "add": false,
              "count": {
                "type": "minecraft:uniform",
                "max": 1.0,
                "min": 0.0
              },
              "function": "minecraft:set_count"
            },
            {
              "count": {
                "type": "minecraft:uniform",
                "max": 1.0,
                "min": 0.0
              },
              "function": "minecraft:looting_enchant"
            }
          ],
          "name": "minecraft:bone"
        },
        {
          "type": "minecraft:item",
          "weight":2,
          "functions": [
            {
              "add": false,
              "count": {
                "type": "minecraft:uniform",
                "max": 1.0,
                "min": 0.0
              },
              "function": "minecraft:set_count"
            },
            {
              "count": {
                "type": "minecraft:uniform",
                "max": 1.0,
                "min": 0.0
              },
              "function": "minecraft:looting_enchant"
            }
          ],
          "name": "minecraft:experience_bottle"
        },
        {
          "type": "empty",
          "weight": 3
        }
      ]
    }
  ]
}