{"stats":{"minecraft:killed":{"minecraft:cave_spider":82,"minecraft:skeleton":292,"minecraft:guardian":12,"minecraft:pillager":5,"minecraft:zombie":202,"minecraft:vindicator":1,"minecraft:husk":271,"minecraft:zombified_piglin":6,"minecraft:witch":5,"minecraft:spider":61,"minecraft:bee":15,"minecraft:creeper":160,"minecraft:ghast":8,"minecraft:stray":83,"minecraft:blaze":15,"minecraft:vex":9,"minecraft:phantom":47,"minecraft:drowned":72,"minecraft:wither_skeleton":61},"minecraft:broken":{"minecraft:chainmail_chestplate":1},"minecraft:mined":{"minecraft:dark_prismarine_stairs":1,"minecraft:blackstone_stairs":1,"minecraft:white_bed":3,"minecraft:jungle_leaves":4,"minecraft:granite":12,"minecraft:light_gray_bed":5,"minecraft:pink_stained_glass":31,"minecraft:deepslate_bricks":10,"minecraft:coal_block":43,"minecraft:crimson_fungus":4,"minecraft:chiseled_stone_bricks":1,"minecraft:spawner":392,"minecraft:light_blue_stained_glass":2,"minecraft:tall_seagrass":80,"minecraft:mossy_cobblestone_stairs":3,"minecraft:cobbled_deepslate":46,"minecraft:sticky_piston":6,"minecraft:fire":206,"minecraft:moss_carpet":9,"minecraft:granite_slab":1,"minecraft:deepslate_lapis_ore":13,"minecraft:twisting_vines":40,"minecraft:lime_stained_glass_pane":7,"minecraft:deepslate_brick_stairs":1,"minecraft:blue_orchid":3,"minecraft:player_head":5,"minecraft:tripwire":9,"minecraft:soul_wall_torch":1,"minecraft:brown_mushroom":2,"minecraft:kelp_plant":21,"minecraft:player_wall_head":7,"minecraft:smoker":6,"minecraft:blue_stained_glass":5,"minecraft:powder_snow":1,"minecraft:torch":15,"minecraft:blast_furnace":6,"minecraft:polished_andesite_stairs":9,"minecraft:creeper_wall_head":3,"minecraft:smooth_quartz_slab":1,"minecraft:cyan_bed":1,"minecraft:amethyst_block":1,"minecraft:skeleton_skull":1,"minecraft:repeater":6,"minecraft:black_concrete_powder":5,"minecraft:mud":1,"minecraft:lilac":1,"minecraft:lime_concrete":1,"minecraft:pitcher_plant":9,"minecraft:grass":168,"minecraft:smooth_quartz":4,"minecraft:stonecutter":1,"minecraft:yellow_stained_glass":1,"minecraft:deepslate":15,"minecraft:dark_prismarine":8,"minecraft:mossy_cobblestone":21,"minecraft:nether_bricks":1,"minecraft:cobbled_deepslate_slab":2,"minecraft:redstone_wire":75,"minecraft:lime_wool":3,"minecraft:moss_block":88,"minecraft:kelp":18,"minecraft:packed_mud":15,"minecraft:red_sandstone":2,"minecraft:potted_torchflower":1,"minecraft:acacia_wood":1,"minecraft:green_terracotta":1,"minecraft:andesite":24,"minecraft:mossy_stone_brick_stairs":1,"minecraft:potatoes":283,"minecraft:cobblestone_slab":1,"minecraft:vine":1,"minecraft:rail":119,"minecraft:bamboo":3,"minecraft:gray_concrete":3,"minecraft:glass_pane":4,"minecraft:cherry_planks":6,"minecraft:soul_sand":3,"minecraft:polished_blackstone_brick_wall":2,"minecraft:fire_coral":1,"minecraft:cobbled_deepslate_wall":2,"minecraft:tall_grass":310,"minecraft:cracked_deepslate_bricks":4,"minecraft:diorite":3,"minecraft:red_terracotta":1,"minecraft:coarse_dirt":3,"minecraft:cobblestone_wall":7,"minecraft:purple_concrete":1,"minecraft:mangrove_leaves":4,"minecraft:dark_prismarine_slab":1,"minecraft:cobweb":32,"minecraft:brown_terracotta":1,"minecraft:polished_blackstone":1,"minecraft:stone_bricks":59,"minecraft:fern":2,"minecraft:prismarine_wall":5,"minecraft:cobbled_deepslate_stairs":1,"minecraft:orange_stained_glass":1,"minecraft:grass_block":6,"minecraft:dead_tube_coral_block":4,"minecraft:gray_banner":2,"minecraft:cracked_polished_blackstone_bricks":12,"minecraft:polished_blackstone_brick_slab":4,"minecraft:mud_bricks":9,"minecraft:raw_iron_block":1,"minecraft:glowstone":9,"minecraft:iron_ore":3,"minecraft:black_carpet":20,"minecraft:skeleton_wall_skull":3,"minecraft:iron_bars":3,"minecraft:black_candle":6,"minecraft:jungle_door":22,"minecraft:blackstone":4,"minecraft:twisting_vines_plant":96,"minecraft:polished_deepslate_stairs":2,"minecraft:clay":3,"minecraft:calcite":54,"minecraft:mossy_cobblestone_wall":1,"minecraft:chest":18,"minecraft:cobblestone":108,"minecraft:prismarine":32,"minecraft:oak_planks":1,"minecraft:wall_torch":18,"minecraft:seagrass":56,"minecraft:lapis_block":6,"minecraft:sand":5,"minecraft:dirt":33,"minecraft:tripwire_hook":2,"minecraft:tube_coral":2,"minecraft:tuff":49,"minecraft:blackstone_wall":1,"minecraft:gray_shulker_box":90,"minecraft:mangrove_roots":2,"minecraft:ladder":2,"minecraft:white_stained_glass":2,"minecraft:polished_andesite_slab":1,"minecraft:cracked_nether_bricks":4,"minecraft:sandstone":1,"minecraft:rooted_dirt":1,"minecraft:large_fern":76,"minecraft:hay_block":12,"minecraft:polished_basalt":2,"minecraft:light_gray_shulker_box":2,"minecraft:black_concrete":2,"minecraft:packed_ice":3,"minecraft:stone":16,"minecraft:redstone_wall_torch":4,"minecraft:scaffolding":204,"minecraft:magenta_stained_glass":3,"minecraft:basalt":9,"minecraft:crafting_table":2,"minecraft:blackstone_slab":3,"minecraft:gray_stained_glass":12,"minecraft:andesite_wall":4,"minecraft:red_nether_brick_wall":2,"minecraft:lapis_ore":110,"minecraft:polished_blackstone_brick_stairs":4,"minecraft:prismarine_bricks":1,"minecraft:cactus":6,"minecraft:sea_pickle":2,"minecraft:redstone_torch":2,"minecraft:ice":1,"minecraft:white_wall_banner":1,"minecraft:muddy_mangrove_roots":5,"minecraft:warped_hyphae":6,"minecraft:dead_brain_coral_block":1,"minecraft:coal_ore":110,"minecraft:end_rod":1,"minecraft:lodestone":1,"minecraft:cracked_stone_bricks":46,"minecraft:polished_andesite":2,"minecraft:mossy_stone_bricks":13},"minecraft:custom":{"minecraft:interact_with_crafting_table":34,"minecraft:open_barrel":90,"minecraft:bell_ring":11,"minecraft:leave_game":24,"minecraft:time_since_death":54675,"minecraft:play_time":1458916,"minecraft:deaths":101,"minecraft:jump":22629,"minecraft:interact_with_furnace":36,"minecraft:traded_with_villager":21,"minecraft:damage_dealt":131336,"minecraft:interact_with_smoker":72,"minecraft:inspect_dispenser":4,"minecraft:interact_with_anvil":12,"minecraft:target_hit":1,"minecraft:sneak_time":63846,"minecraft:interact_with_blast_furnace":36,"minecraft:total_world_time":1458916,"minecraft:tune_noteblock":4,"minecraft:time_since_rest":54696,"minecraft:swim_one_cm":854347,"minecraft:fly_one_cm":5405511,"minecraft:open_chest":1776,"minecraft:fall_one_cm":1901537,"minecraft:open_shulker_box":391,"minecraft:damage_resisted":2983,"minecraft:sprint_one_cm":5521759,"minecraft:drop":374,"minecraft:talked_to_villager":27,"minecraft:walk_on_water_one_cm":224521,"minecraft:open_enderchest":98,"minecraft:crouch_one_cm":166714,"minecraft:mob_kills":1798,"minecraft:damage_dealt_resisted":15865,"minecraft:climb_one_cm":229913,"minecraft:walk_one_cm":4163042,"minecraft:walk_under_water_one_cm":415998,"minecraft:pot_flower":1,"minecraft:damage_taken":82403,"minecraft:damage_absorbed":2481,"minecraft:trigger_trapped_chest":10},"minecraft:dropped":{"minecraft:clay":24,"minecraft:lapis_lazuli":67,"minecraft:glass_bottle":1,"minecraft:cooked_porkchop":1,"minecraft:red_sandstone":2,"minecraft:mossy_stone_brick_stairs":1,"minecraft:cracked_stone_bricks":4,"minecraft:rail":35,"minecraft:blackstone_stairs":2,"minecraft:leather_helmet":1,"minecraft:red_carpet":10,"minecraft:packed_mud":3,"minecraft:gray_concrete":1,"minecraft:jungle_sapling":1,"minecraft:chain":6,"minecraft:bone_meal":147,"minecraft:polished_blackstone_slab":1,"minecraft:lever":1,"minecraft:polished_andesite_slab":2,"minecraft:cobbled_deepslate":2,"minecraft:black_carpet":20,"minecraft:glowstone_dust":4,"minecraft:end_stone":4,"minecraft:warped_planks":5,"minecraft:leather_boots":1,"minecraft:leather_leggings":1,"minecraft:painting":4,"minecraft:stone_brick_stairs":3,"minecraft:infested_cobblestone":1,"minecraft:dead_tube_coral_block":4,"minecraft:chiseled_nether_bricks":1,"minecraft:wheat_seeds":9,"minecraft:cobbled_deepslate_stairs":5,"minecraft:polished_blackstone":3,"minecraft:cobblestone":7,"minecraft:prismarine_crystals":2,"minecraft:purple_concrete":1,"minecraft:purple_dye":1,"minecraft:polished_blackstone_stairs":1,"minecraft:polished_andesite":3,"minecraft:end_rod":2,"minecraft:cobweb":4,"minecraft:brown_concrete_powder":6,"minecraft:blackstone_wall":1,"minecraft:cooked_salmon":7,"minecraft:brown_terracotta":8,"minecraft:smooth_sandstone":3,"minecraft:red_nether_brick_wall":2,"minecraft:moss_carpet":28,"minecraft:soul_torch":1,"minecraft:stone_sword":3,"minecraft:cobblestone_wall":22,"minecraft:polished_deepslate_slab":2,"minecraft:clay_ball":14,"minecraft:stone_slab":3,"minecraft:magenta_concrete":1,"minecraft:cobbled_deepslate_slab":13,"minecraft:polished_deepslate_stairs":3,"minecraft:polished_granite_stairs":2,"minecraft:potato":290,"minecraft:sea_pickle":2,"minecraft:redstone_torch":5,"minecraft:stone_bricks":8,"minecraft:brown_carpet":28,"minecraft:sandstone":6,"minecraft:blue_orchid":5,"minecraft:bow":2,"minecraft:magma_block":6,"minecraft:dark_prismarine":5,"minecraft:spruce_sign":1,"minecraft:soul_sand":4,"minecraft:moss_block":8,"minecraft:brown_mushroom":2,"minecraft:polished_granite_slab":1,"minecraft:baked_potato":43,"minecraft:sandstone_slab":1,"minecraft:leather":1,"minecraft:prismarine_brick_stairs":1,"minecraft:mangrove_planks":1,"minecraft:mossy_cobblestone_wall":1,"minecraft:polished_blackstone_brick_wall":2,"minecraft:carrot_on_a_stick":18,"minecraft:cobblestone_stairs":1,"minecraft:flint":2,"minecraft:cyan_terracotta":3,"minecraft:cracked_polished_blackstone_bricks":6,"minecraft:polished_blackstone_brick_stairs":6,"minecraft:cooked_cod":14,"minecraft:snowball":11,"minecraft:polished_blackstone_bricks":1,"minecraft:black_concrete":2,"minecraft:lime_wool":1,"minecraft:chainmail_chestplate":1,"minecraft:chiseled_stone_bricks":2,"minecraft:leather_chestplate":1,"minecraft:trident":6,"minecraft:lingering_potion":3,"minecraft:blackstone_slab":1,"minecraft:basalt":3,"minecraft:iron_bars":10,"minecraft:gray_shulker_box":1,"minecraft:arrow":238,"minecraft:prismarine_bricks":1,"minecraft:cracked_nether_bricks":9,"minecraft:prismarine_wall":2,"minecraft:stone_hoe":1,"minecraft:mossy_cobblestone":3,"minecraft:cyan_dye":7,"minecraft:andesite_wall":7,"minecraft:stick":3,"minecraft:mossy_cobblestone_slab":10,"minecraft:diorite":2,"minecraft:torch":73,"minecraft:smooth_quartz":2,"minecraft:light_gray_shulker_box":1,"minecraft:polished_blackstone_brick_slab":8,"minecraft:polished_andesite_stairs":2,"minecraft:granite_slab":3,"minecraft:stonecutter":1,"minecraft:polished_basalt":4,"minecraft:cactus":1,"minecraft:dark_prismarine_stairs":3,"minecraft:coarse_dirt":1,"minecraft:tuff":4,"minecraft:deepslate_bricks":3,"minecraft:gray_terracotta":1,"minecraft:end_stone_brick_stairs":1,"minecraft:iron_chestplate":1,"minecraft:andesite":4,"minecraft:mossy_stone_bricks":3,"minecraft:gray_concrete_powder":12,"minecraft:stone_pickaxe":2,"minecraft:dead_brain_coral_block":3,"minecraft:cracked_deepslate_bricks":2,"minecraft:calcite":1},"minecraft:used":{"minecraft:moss_block":82,"minecraft:nether_brick_fence":1,"minecraft:smooth_quartz_slab":1,"minecraft:dead_horn_coral_block":3,"minecraft:polished_blackstone":4,"minecraft:ladder":6,"minecraft:black_carpet":1,"minecraft:chest":15,"minecraft:warped_sign":1,"minecraft:rotten_flesh":4,"minecraft:soul_sand":1,"minecraft:polished_blackstone_slab":1,"minecraft:mangrove_stairs":1,"minecraft:bow":88,"minecraft:furnace":2,"minecraft:cooked_cod":8,"minecraft:gray_banner":2,"minecraft:potato":196,"minecraft:mossy_stone_bricks":82,"minecraft:diorite":5,"minecraft:leather_leggings":2,"minecraft:blackstone_stairs":1,"minecraft:prismarine":209,"minecraft:blackstone":2,"minecraft:clay":127,"minecraft:sand":5,"minecraft:blast_furnace":6,"minecraft:gray_concrete":6,"minecraft:red_sandstone":15,"minecraft:chiseled_sandstone":9,"minecraft:lilac":4,"minecraft:polished_andesite_slab":1,"minecraft:soul_lantern":1,"minecraft:pink_stained_glass":38,"minecraft:polished_blackstone_brick_slab":2,"minecraft:stone_sword":694,"minecraft:dead_tube_coral_block":4,"minecraft:orange_concrete":1,"minecraft:cooked_salmon":25,"minecraft:sandstone_wall":5,"minecraft:light_gray_shulker_box":1,"minecraft:torch":2586,"minecraft:chainmail_chestplate":7,"minecraft:stone_stairs":4,"minecraft:dead_brain_coral_block":41,"minecraft:polished_diorite":3,"minecraft:shroomlight":3,"minecraft:mossy_cobblestone_stairs":3,"minecraft:sea_lantern":12,"minecraft:muddy_mangrove_roots":47,"minecraft:rooted_dirt":1,"minecraft:mud_bricks":132,"minecraft:basalt":86,"minecraft:glowstone":490,"minecraft:lime_concrete":2,"minecraft:cobbled_deepslate":170,"minecraft:calcite":70,"minecraft:water_bucket":83,"minecraft:lime_wool":1,"minecraft:cherry_planks":115,"minecraft:deepslate_bricks":86,"minecraft:polished_blackstone_bricks":3,"minecraft:cracked_stone_bricks":173,"minecraft:pink_concrete":1,"minecraft:mossy_cobblestone":27,"minecraft:rail":166,"minecraft:crafting_table":7,"minecraft:white_bed":3,"minecraft:mud":10,"minecraft:dark_prismarine":9,"minecraft:iron_pickaxe":172,"minecraft:leather_helmet":1,"minecraft:spruce_trapdoor":1,"minecraft:chiseled_stone_bricks":1,"minecraft:cobblestone":351,"minecraft:potion":30,"minecraft:cooked_porkchop":19,"minecraft:black_candle":12,"minecraft:moss_carpet":2,"minecraft:red_sand":2,"minecraft:carrot_on_a_stick":317,"minecraft:polished_basalt":7,"minecraft:iron_sword":148,"minecraft:creeper_head":3,"minecraft:player_head":12,"minecraft:green_terracotta":4,"minecraft:iron_chestplate":1,"minecraft:jungle_planks":8,"minecraft:nether_bricks":15,"minecraft:prismarine_brick_stairs":2,"minecraft:tuff":69,"minecraft:cyan_terracotta":2,"minecraft:blue_orchid":1,"minecraft:packed_mud":13,"minecraft:polished_blackstone_brick_wall":3,"minecraft:mossy_cobblestone_slab":4,"minecraft:gray_concrete_powder":8,"minecraft:stone_bricks":64,"minecraft:item_frame":3,"minecraft:bedrock":24,"minecraft:magma_block":6,"minecraft:written_book":4,"minecraft:scaffolding":428,"minecraft:mangrove_roots":2,"minecraft:blue_shulker_box":1,"minecraft:skeleton_skull":6,"minecraft:pearlescent_froglight":10,"minecraft:polished_blackstone_stairs":1,"minecraft:stone_pickaxe":1454,"minecraft:oak_planks":1,"minecraft:sandstone":6,"minecraft:chainmail_helmet":1,"minecraft:yellow_concrete":1,"minecraft:lingering_potion":973,"minecraft:end_stone":6,"minecraft:cobbled_deepslate_stairs":2,"minecraft:redstone_torch":1,"minecraft:gray_shulker_box":88,"minecraft:cyan_bed":1,"minecraft:bread":17,"minecraft:gravel":24,"minecraft:blackstone_slab":5,"minecraft:chainmail_boots":3,"minecraft:cooked_rabbit":22,"minecraft:andesite":32,"minecraft:mossy_cobblestone_wall":1,"minecraft:coarse_dirt":5,"minecraft:bone_meal":184,"minecraft:experience_bottle":161,"minecraft:trident":1939,"minecraft:orange_concrete_powder":4,"minecraft:cracked_deepslate_bricks":4,"minecraft:stone_shovel":6,"minecraft:stone_hoe":283,"minecraft:dirt":197,"minecraft:spyglass":76,"minecraft:prismarine_bricks":1,"minecraft:cobblestone_wall":5,"minecraft:warped_door":4,"minecraft:granite":11,"minecraft:andesite_wall":1,"minecraft:brown_terracotta":3,"minecraft:emerald_block":1,"minecraft:soul_soil":15,"minecraft:pitcher_plant":8,"minecraft:cooked_beef":36,"minecraft:light_gray_bed":6,"minecraft:cobbled_deepslate_wall":1,"minecraft:amethyst_block":65,"minecraft:snow_block":16,"minecraft:glass_bottle":2,"minecraft:polished_andesite":1,"minecraft:red_nether_bricks":3,"minecraft:baked_potato":624,"minecraft:mud_brick_slab":2,"minecraft:magenta_stained_glass":22,"minecraft:dark_prismarine_slab":2,"minecraft:painting":4,"minecraft:smoker":6,"minecraft:warped_planks":49,"minecraft:gray_terracotta":14,"minecraft:flower_pot":1,"minecraft:apple":1,"minecraft:cherry_door":3,"minecraft:cracked_polished_blackstone_bricks":14,"minecraft:cracked_nether_bricks":4,"minecraft:magenta_concrete":2,"minecraft:purple_dye":1,"minecraft:stone_axe":287,"minecraft:crimson_fungus":2,"minecraft:cobbled_deepslate_slab":2,"minecraft:white_banner":1,"minecraft:jungle_door":38,"minecraft:bucket":84,"minecraft:splash_potion":1,"minecraft:chainmail_leggings":2},"minecraft:crafted":{"minecraft:iron_pickaxe":1,"minecraft:prismarine":2,"minecraft:leather_leggings":1,"minecraft:bone_meal":141,"minecraft:stone_pickaxe":2,"minecraft:splash_potion":3,"minecraft:glowstone":8,"minecraft:chainmail_boots":1,"minecraft:oak_planks":12,"minecraft:red_sandstone":15,"minecraft:warped_planks":180,"minecraft:chest":1,"minecraft:arrow":129,"minecraft:crafting_table":5,"minecraft:spruce_planks":4,"minecraft:baked_potato":139,"minecraft:chainmail_chestplate":1,"minecraft:warped_door":6,"minecraft:stick":528,"minecraft:snow_block":30,"minecraft:cherry_planks":240,"minecraft:coal":423,"minecraft:furnace":2,"minecraft:scaffolding":24,"minecraft:mangrove_planks":4,"minecraft:bucket":1,"minecraft:air":0,"minecraft:jungle_planks":100,"minecraft:jungle_door":15,"minecraft:cherry_door":3,"minecraft:torch":2276,"minecraft:acacia_planks":24,"minecraft:lapis_lazuli":324,"minecraft:clay":215,"minecraft:lapis_block":107},"minecraft:picked_up":{"minecraft:iron_chestplate":1,"minecraft:chainmail_boots":3,"minecraft:creeper_head":3,"minecraft:flower_pot":1,"minecraft:prismarine_shard":16,"minecraft:stone_slab":2,"minecraft:amethyst_block":48,"minecraft:dark_oak_pressure_plate":2,"minecraft:polished_blackstone_brick_stairs":13,"minecraft:string":247,"minecraft:soul_soil":15,"minecraft:cooked_salmon":134,"minecraft:red_nether_bricks":6,"minecraft:orange_concrete_powder":60,"minecraft:cobbled_deepslate":491,"minecraft:written_book":32,"minecraft:coal_block":193,"minecraft:polished_blackstone_brick_slab":7,"minecraft:polished_blackstone_stairs":8,"minecraft:warped_planks":164,"minecraft:green_terracotta":4,"minecraft:gray_shulker_box":162,"minecraft:warped_door":4,"minecraft:chiseled_nether_bricks":1,"minecraft:brown_carpet":29,"minecraft:stone_sword":30,"minecraft:light_gray_bed":5,"minecraft:polished_basalt":24,"minecraft:blackstone_wall":2,"minecraft:cyan_terracotta":23,"minecraft:glowstone":834,"minecraft:end_rod":14,"minecraft:blackstone_stairs":8,"minecraft:iron_bars":22,"minecraft:snowball":162,"minecraft:magma_block":25,"minecraft:mossy_cobblestone_slab":7,"minecraft:cooked_beef":227,"minecraft:water_bucket":42,"minecraft:jungle_log":66,"minecraft:smoker":6,"minecraft:flint":5,"minecraft:gray_concrete":8,"minecraft:gray_concrete_powder":107,"minecraft:twisting_vines":892,"minecraft:warped_hyphae":66,"minecraft:gray_terracotta":27,"minecraft:stonecutter":7,"minecraft:glowstone_dust":60,"minecraft:moss_block":121,"minecraft:granite_slab":2,"minecraft:polished_andesite":2,"minecraft:black_concrete_powder":174,"minecraft:lever":1,"minecraft:polished_granite_slab":2,"minecraft:dead_brain_coral_block":5,"minecraft:granite":83,"minecraft:bread":12,"minecraft:chainmail_helmet":2,"minecraft:cyan_dye":109,"minecraft:rooted_dirt":2,"minecraft:bricks":2,"minecraft:crafting_table":2,"minecraft:mud":23,"minecraft:coarse_dirt":5,"minecraft:sandstone_slab":1,"minecraft:clay_ball":864,"minecraft:leather_leggings":3,"minecraft:infested_cobblestone":2,"minecraft:dead_horn_coral_block":108,"minecraft:cracked_stone_bricks":380,"minecraft:jungle_sapling":1,"minecraft:spruce_slab":4,"minecraft:chest":27,"minecraft:sandstone":12,"minecraft:polished_deepslate_slab":2,"minecraft:spruce_fence":2,"minecraft:redstone":289,"minecraft:red_nether_brick_wall":3,"minecraft:prismarine_crystals":2,"minecraft:polished_granite_stairs":4,"minecraft:deepslate_bricks":480,"minecraft:hay_block":12,"minecraft:cracked_deepslate_bricks":25,"minecraft:warped_sign":1,"minecraft:polished_blackstone":16,"minecraft:rail":401,"minecraft:mud_bricks":51,"minecraft:tripwire_hook":2,"minecraft:blackstone_slab":13,"minecraft:acacia_wood":23,"minecraft:ochre_froglight":1,"minecraft:packed_mud":68,"minecraft:torchflower":1,"minecraft:lily_pad":10,"minecraft:white_banner":1,"minecraft:stone_bricks":874,"minecraft:apple":27,"minecraft:kelp":51,"minecraft:stone_pickaxe":7,"minecraft:cobweb":148,"minecraft:mangrove_planks":69,"minecraft:iron_sword":5,"minecraft:polished_andesite_stairs":10,"minecraft:prismarine_brick_stairs":7,"minecraft:yellow_concrete":1,"minecraft:cracked_nether_bricks":42,"minecraft:lime_concrete":1,"minecraft:spyglass":42,"minecraft:gravel":201,"minecraft:crying_obsidian":36,"minecraft:sea_lantern":37,"minecraft:oak_wood":3,"minecraft:stone_axe":9,"minecraft:polished_diorite":1,"minecraft:painting":13,"minecraft:polished_blackstone_brick_wall":3,"minecraft:lodestone":2,"minecraft:baked_potato":368,"minecraft:smooth_quartz_slab":5,"minecraft:black_carpet":33,"minecraft:light_gray_shulker_box":2,"minecraft:nether_brick_fence":1,"minecraft:potion":4,"minecraft:stone_brick_stairs":4,"minecraft:lapis_block":10,"minecraft:dead_tube_coral_block":8,"minecraft:smooth_stone_slab":4,"minecraft:sticky_piston":26,"minecraft:experience_bottle":1128,"minecraft:oak_sign":1,"minecraft:sea_pickle":14,"minecraft:red_sand":176,"minecraft:bucket":2,"minecraft:redstone_torch":19,"minecraft:cobblestone_slab":9,"minecraft:calcite":73,"minecraft:smooth_quartz":4,"minecraft:stick":87,"minecraft:jungle_door":29,"minecraft:brown_terracotta":22,"minecraft:polished_deepslate_stairs":1,"minecraft:torch":951,"minecraft:snow_block":64,"minecraft:diorite":8,"minecraft:pointed_dripstone":3,"minecraft:andesite_wall":17,"minecraft:cactus":31,"minecraft:mangrove_stairs":4,"minecraft:rotten_flesh":28,"minecraft:mangrove_roots":2,"minecraft:deepslate_brick_stairs":6,"minecraft:cobblestone":1011,"minecraft:leather_chestplate":2,"minecraft:muddy_mangrove_roots":3,"minecraft:repeater":16,"minecraft:cherry_planks":921,"minecraft:andesite":113,"minecraft:orange_carpet":1,"minecraft:potato":1238,"minecraft:tuff":115,"minecraft:prismarine_bricks":5,"minecraft:lapis_lazuli":2811,"minecraft:dirt":384,"minecraft:polished_granite":2,"minecraft:leather_boots":3,"minecraft:bone":450,"minecraft:acacia_planks":54,"minecraft:bow":25,"minecraft:cobbled_deepslate_wall":1,"minecraft:wheat_seeds":6,"minecraft:cobbled_deepslate_slab":18,"minecraft:mossy_stone_brick_stairs":1,"minecraft:mossy_stone_bricks":286,"minecraft:bamboo":8,"minecraft:prismarine":117,"minecraft:stone_hoe":1,"minecraft:oak_planks":1,"minecraft:pink_stained_glass":130,"minecraft:cooked_porkchop":25,"minecraft:poisonous_potato":2,"minecraft:polished_blackstone_slab":9,"minecraft:jungle_planks":94,"minecraft:sand":6,"minecraft:cyan_bed":1,"minecraft:chiseled_sandstone":4,"minecraft:mossy_cobblestone":57,"minecraft:dark_prismarine":50,"minecraft:dark_prismarine_slab":2,"minecraft:yellow_carpet":3,"minecraft:clay":376,"minecraft:black_concrete":2,"minecraft:soul_lantern":3,"minecraft:cherry_wood":339,"minecraft:cracked_polished_blackstone_bricks":49,"minecraft:bone_meal":191,"minecraft:spruce_sign":3,"minecraft:emerald":4,"minecraft:lingering_potion":39,"minecraft:mud_brick_slab":2,"minecraft:end_stone_brick_stairs":2,"minecraft:splash_potion":26,"minecraft:ladder":29,"minecraft:brown_mushroom":12,"minecraft:cooked_rabbit":120,"minecraft:chain":174,"minecraft:moss_carpet":39,"minecraft:stone_stairs":1,"minecraft:item_frame":1,"minecraft:blackstone":13,"minecraft:blue_orchid":22,"minecraft:dark_prismarine_stairs":3,"minecraft:mossy_cobblestone_wall":7,"minecraft:player_head":13,"minecraft:blue_shulker_box":5,"minecraft:spruce_trapdoor":1,"minecraft:lime_wool":2,"minecraft:raw_iron":9,"minecraft:end_stone":19,"minecraft:polished_blackstone_bricks":4,"minecraft:trident":15,"minecraft:iron_horse_armor":35,"minecraft:arrow":2304,"minecraft:nether_bricks":27,"minecraft:skeleton_skull":27,"minecraft:purple_dye":147,"minecraft:basalt":126,"minecraft:leather":403,"minecraft:carrot_on_a_stick":31,"minecraft:crimson_fungus":22,"minecraft:chainmail_chestplate":3,"minecraft:cobbled_deepslate_stairs":23,"minecraft:cobblestone_wall":43,"minecraft:cobblestone_stairs":14,"minecraft:red_carpet":12,"minecraft:pearlescent_froglight":430,"minecraft:red_sandstone":5,"minecraft:iron_ingot":3,"minecraft:polished_andesite_slab":7,"minecraft:verdant_froglight":32,"minecraft:soul_sand":5,"minecraft:purple_concrete":1,"minecraft:book":129,"minecraft:scaffolding":3495,"minecraft:black_candle":12,"minecraft:emerald_block":1,"minecraft:pitcher_plant":24,"minecraft:chiseled_stone_bricks":3,"minecraft:raw_iron_block":1,"minecraft:soul_torch":1,"minecraft:blast_furnace":11,"minecraft:white_bed":3,"minecraft:prismarine_wall":12,"minecraft:gray_banner":2,"minecraft:chainmail_leggings":1,"minecraft:mossy_cobblestone_stairs":4,"minecraft:magenta_concrete":4,"minecraft:coal":1797},"minecraft:killed_by":{"minecraft:zombie":5,"minecraft:vex":3,"minecraft:husk":4,"minecraft:stray":12,"minecraft:armor_stand":5,"minecraft:guardian":3,"minecraft:wither_skeleton":16,"minecraft:creeper":20,"minecraft:drowned":9,"minecraft:spider":1,"minecraft:skeleton":13,"minecraft:phantom":1}},"DataVersion":3465}